{
    "url": "https://www.samsung.com/pk/smartphones/galaxy-a/galaxy-a36-5g-awesome-white-256gb-sm-a366bzavpkd/",
    "title": "Galaxy A36 5G Awesome White 256Gb Sm A366Bzavpkd",
    "category": "Smartphones",
    "features": [
        "Slimmer design with a stylish twist",
        "Make a statement with a mix of minimalism and durability with Galaxy A36 5G. Featuring a clean, linear grouped camera layout with a premium glass back. Built with a slimmer  bezel and flat side frame, offering a slim, stylish feel and finish.",
        "Be different, be colorful, be you",
        "Show up and show out with four distinctive colors. From playful Awesome Lavender to Awesome Lime, or  Awesome White to Awesome Black, pick the ideal hue for you.",
        "Awesome larger 6.7” display for immersive gameplay",
        "Watch the latest shows on a larger, 6.7\" FHD+ Super AMOLED display. With a 120 Hz refresh rate and increased brightness of 1,200 nits, enjoy smooth scrolling and better visibility, even when outdoors.",
        "Improved cameras for more creativity",
        ".",
        "Strong durability",
        "Corning® Gorilla® Glass Victus®+ keep the Awesome design of Galaxy A36 5G looking great. Plus, with IP67 protection, the new Galaxy A series is safe from dirt and splashes."
    ],
    "specifications": {
        "Weight (g)": "195",
        "CPU Speed": "2.4GHz, 1.8GHz",
        "CPU Type": "Octa-Core",
        "Size (Main_Display)": "170.1mm (6.7\")",
        "Resolution (Main Display)": "1080 x 2340 (FHD+)",
        "Technology (Main Display)": "Super AMOLED",
        "Color Depth (Main Display)": "16M",
        "Max Refresh Rate (Main Display)": "120 Hz",
        "Rear Camera - Resolution (Multiple)": "50.0 MP + 8.0 MP + 5.0 MP",
        "Rear Camera - F Number (Multiple)": "F1.8 , F2.2 , F2.4",
        "Rear Camera - Auto Focus": "Yes",
        "Rear Camera - OIS": "Yes",
        "Rear Camera Zoom": "Digital Zoom up to 10x",
        "Front Camera - Resolution": "12.0 MP",
        "Front Camera - F Number": "F2.2",
        "Front Camera - Auto Focus": "No",
        "Front Camera - OIS": "No",
        "Rear Camera - Flash": "Yes",
        "Front Camera - Flash": "No",
        "Video Recording Resolution": "UHD 4K (3840 x 2160) @30fps",
        "Slow Motion": "240fps @HD",
        "Memory_(GB)": "8",
        "Storage (GB)": "256",
        "Available Storage (GB)": "233.2",
        "Number of SIM": "Dual-SIM",
        "SIM size": "Nano-SIM (4FF), Embedded-SIM",
        "SIM Slot Type": "SIM 1 + SIM 2 / SIM 1 + eSIM / Dual eSIM",
        "Infra": "2G GSM, 3G WCDMA, 4G LTE FDD, 4G LTE TDD, 5G Sub6 FDD, 5G Sub6 TDD",
        "2G GSM": "GSM850, GSM900, DCS1800, PCS1900",
        "3G UMTS": "B1(2100), B2(1900), B4(AWS), B5(850), B8(900)",
        "4G FDD LTE": "B1(2100), B2(1900), B3(1800), B4(AWS), B5(850), B7(2600), B8(900), B12(700), B17(700), B20(800), B25(1900), B26(850), B28(700), B66(AWS-3)",
        "4G TDD LTE": "B38(2600), B40(2300), B41(2500)",
        "5G FDD Sub6": "N1(2100), N3(1800), N5(850), N7(2600), N8(900), N20(800), N26(850), N28(700), N66(AWS-3), N71(600)",
        "5G TDD Sub6": "N40(2300), N41(2500), N77(3700), N78(3500)",
        "USB Interface": "USB Type-C",
        "USB Version": "USB 2.0",
        "Location Technology": "GPS, Glonass, Beidou, Galileo, QZSS",
        "Earjack": "USB Type-C",
        "MHL": "No",
        "Wi-Fi": "802.11a/b/g/n/ac/ax 2.4GHz+5GHz, HE80, MIMO, 1024-QAM",
        "Wi-Fi Direct": "Yes",
        "Bluetooth Version": "Bluetooth v5.4",
        "PC Sync.": "Smart Switch (PC version)",
        "Form Factor": "Touch Bar",
        "Dimension (HxWxD, mm)": "162.9 x 78.2 x 7.4",
        "Video Playback Time (Hours)": "Up to 29",
        "Battery Capacity (mAh, Typical)": "5000",
        "Removable": "No",
        "Stereo Support": "Yes",
        "Video Playing Format": "MP4, M4V, 3GP, 3G2, AVI, FLV, MKV, WEBM",
        "Video Playing Resolution": "UHD 4K (3840 x 2160) @30fps",
        "Audio Playing Format": "MP3, M4A, 3GA, AAC, OGG, OGA, WAV, AMR, AWB, FLAC, MID, MIDI, XMF, MXMF, IMY, RTTTL, RTX, OTA",
        "Gear Support": "Galaxy Ring, Galaxy Buds3 Pro, Galaxy Buds2 Pro, Galaxy Buds Pro, Galaxy Buds Live, Galaxy Buds+, Galaxy Buds3, Galaxy Buds2, Galaxy Buds, Galaxy Buds FE, Galaxy Fit3, Galaxy Fit2, Galaxy Fit e, Galaxy Fit, Galaxy Watch FE, Galaxy Watch Ultra, Galaxy Watch7, Galaxy Watch6, Galaxy Watch5, Galaxy Watch4, Galaxy Watch3, Galaxy Watch, Galaxy Watch Active2, Galaxy Watch Active",
        "Samsung DeX Support": "No",
        "Bluetooth® Hearing Aid Support": "Android Audio Streaming for Hearing Aid(ASHA)",
        "SmartThings Support": "Yes",
        "Mobile TV": "No",
        "Security Update Period (Valid until)": "31 March 2031"
    }
}