{
    "url": "https://www.samsung.com/pk/tvs/qled-tv/qn800d-75-inch-neo-qled-8k-tizen-os-smart-tv-qa75qn800dusmm/",
    "title": "Qn800D 75 Inch Neo Qled 8K Tizen Os Smart Tv Qa75Qn800Dusmm",
    "category": "Tvs",
    "features": [
        "\"Samsung's AI-powered upscaling converts 1080P and 4K content into a better version for the QN800D.\"“The gaming performance is great with the benefit of upscaling, high refresh rates and an AI-powered game mode.\"",
        "Upscale every moment with more Wow",
        "NQ8 AI Gen2 Processor",
        "Samsung's AI-powered 8K processor creates one of the best 8K experiences. Our 8K AI Upscaling technology powered by 256 AI neural networks transforms content into near 8K picture quality. Our NQ8 AI Gen2 Processor optimizes both picture and sound to deliver an 8K experience whether you are streaming OTT services, playing your favorite video games or watching live sports.",
        "8K AI Upscaling",
        "Our 8K AI Upscaling technology powered by 256 AI neural networks transforms content into near 8K resolution. Our NQ8 AI Gen2 Processor enables one of the sharpest and smoothest picture qualities in any Samsung TV.",
        "Quantum Matrix Technology Pro",
        "The powerful evolution of Neo QLED 8K reveals unimaginable details expressed in both the darkest blacks to the purest whites with x1.5 more lighting zones than normal Quantum Matrix Technology. Our backlight dimming technology can precisely control our proprietary Quantum Mini LEDs, which enables greater detail in both the darkest and brightest scenes.",
        "Samsung Tizen OS",
        "Get more out of your TV with the latest apps & services on Samsung Tizen OS. Enjoy free live TV channels and thousands of movies with Samsung TV Plus, and seamless cloud gaming with Gaming Hub. You can even manage your daily activities with Daily+ and control your smart devices from your TV with SmartThings."
    ],
    "specifications": {
        "Product Type": "NeoQLED",
        "Refresh Rate": "100Hz",
        "Resolution": "8K (7,680 x 4,320)",
        "Display": "75\"",
        "Screen Size": "75\"",
        "Anti Reflection": "Yes",
        "Picture Engine": "NQ8 AI Gen2 Processor",
        "HDR (High Dynamic Range)": "Neo Quantum HDR 8K+",
        "HDR 10+": "Yes (ADAPTIVE/ GAMING)",
        "AI Upscale": "8K AI Upscaling",
        "Contrast": "Quantum Matrix Technology Pro",
        "Viewing Angle": "Ultra Viewing Angle",
        "Micro Dimming": "Ultimate 8K Dimming Pro",
        "Contrast Enhancer": "Real Depth Enhancer Pro",
        "Motion Technology": "Motion Xcelerator 120Hz",
        "Smart Calibration": "Basic/Professional",
        "Filmmaker Mode (FMM)": "Yes",
        "AI Motion Enhancer": "AI Motion Enhancer",
        "HDR Brightness Optimizer": "Yes",
        "AI HDR Remastering": "Auto HDR Remastering",
        "Dolby Atmos": "Yes",
        "Object Tracking Sound": "OTS+",
        "Q-Symphony": "Yes",
        "Sound Output (RMS)": "70W",
        "Speaker Type": "4.2.2CH",
        "Multiroom Link": "No",
        "Active Voice Amplifier Pro": "Yes",
        "Adaptive Sound": "Adaptive Sound Pro",
        "360 Audio": "Yes",
        "Operating System": "Tizen™ Smart TV",
        "Bixby": "Yes",
        "Far-Field Voice Interaction": "Yes",
        "Web Browser": "Yes",
        "SmartThings Hub / Matter Hub / IoT-Sensor Functionality / Quick Remote": "Yes",
        "Multi Device Experience": "TV to Mobile, Mobile to TV, TV initiate mirroring, Sound Mirroring, Wireless TV On, Tap View",
        "Multi-View": "upto 4 videos",
        "Ambience": "Ambient Mode+",
        "NFT": "Nifty Gateway",
        "Apple AirPlay": "Yes (w/o Syrian Arab Republic, Yemen)",
        "Daily+": "Yes",
        "Auto Game Mode (ALLM)": "Yes",
        "Game Motion Plus": "Yes",
        "Dynamic Black EQ": "Yes",
        "VRR": "Yes",
        "Surround Sound": "Yes",
        "Super Ultra Wide Game View": "Yes",
        "Mini Map Zoom": "Yes",
        "FreeSync": "FreeSync Premium Pro",
        "Light-sync": "Yes (AE only)",
        "HGiG": "Yes",
        "Digital Broadcasting": "DVB-T2CS2",
        "Analog Tuner": "Yes",
        "TV Key Support": "Yes",
        "HDMI": "4",
        "USB": "3 x USB-A, 1 x USB-C",
        "HDMI (High Frame Rate)": "8K 60Hz, 4K 120Hz (for HDMI 1/2/3/4)",
        "Ethernet (LAN)": "1",
        "Digital Audio Out (Optical)": "1",
        "RF In (Terrestrial / Cable input)": "1/1(Common Use for Terrestrial)/1",
        "Wi-Fi": "Yes (Wi-Fi 6)",
        "Bluetooth": "Yes (BT5.3)",
        "Anynet+ (HDMI-CEC)": "Yes",
        "HDMI Audio Return Channel": "eARC",
        "One Connect Box": "One Connect (Y24 8K)",
        "Design": "Infinity One",
        "Bezel Type": "4 Bezel-less",
        "Slim Type": "Ultra Slim",
        "Front Color": "GRAPHITE BLACK",
        "Stand Type": "SLIM OC STAND",
        "Stand Color": "TITAN BLACK",
        "Knox Vault": "Yes",
        "Embeded POP": "Yes",
        "EPG": "Yes",
        "Extended PVR": "Yes",
        "IP Control": "Yes",
        "OSD Language": "Local Languages",
        "Voice Guide": "UK English, France French, Korean, Russian, Hindi",
        "Low Vision Support": "Relumino, Magnification, Audio Description, Zoom Menu and Text, High Contrast, SeeColors, Color Inversion, Grayscale, Picture Off",
        "Hearing Impaired Support": "Closed Caption (Subtitle), Multi-output Audio, Sign Language Zoom",
        "Motor Impaired Support": "Slow Button Repeat, Remote Control App. for All",
        "Eco Sensor": "Yes",
        "Power Supply": "AC100-240V~ 50/60Hz",
        "Power Consumption (Max)": "395 W",
        "Auto Power Off": "Yes",
        "Auto Power Saving": "Yes",
        "Package Size (WxHxD)": "1844.0 x 1124.0 x 191.0 mm",
        "Set Size with Stand (WxHxD)": "1668.3 x 1023.8 x 286.4 mm",
        "Set Size without Stand (WxHxD)": "1668.3 x 955.6 x 17.6 mm",
        "Stand (Basic) (WxD)": "360 x 286.4 mm",
        "VESA Spec": "400 x 400 mm",
        "Package Weight": "57.0 kg",
        "Set Weight with Stand": "43.7 kg",
        "Set Weight without Stand": "31.9 kg",
        "Remote Controller Model": "TM2360E",
        "Slim Fit Wall-mount Support": "Yes",
        "User Manual": "Yes",
        "Full Motion Slim Wall Mount (Y22)": "Yes",
        "Webcam Support": "Yes",
        "Zigbee / Thread Module": "Built-In",
        "Power Cable": "Yes"
    }
}